restlib2
tests
