Metadata-Version: 1.1
Name: restlib2
Version: 0.4.2
Summary: Django REST API
Home-page: https://github.com/bruth/restlib2
Author: Byron Ruth
Author-email: b@devel.io
License: BSD
Keywords: REST Django HTTP HATEOAS
Platform: UNKNOWN
Classifier: Development Status :: 5 - Production/Stable
Classifier: Framework :: Django
Classifier: Intended Audience :: Developers
Classifier: Intended Audience :: System Administrators
Classifier: License :: OSI Approved :: BSD License
Classifier: Operating System :: OS Independent
Classifier: Topic :: Internet :: WWW/HTTP
Classifier: Programming Language :: Python :: 2.6
Classifier: Programming Language :: Python :: 2.7
Classifier: Programming Language :: Python :: 3.2
Classifier: Programming Language :: Python :: 3.3
